baekjoon_solver/main.py
baekjoon_solver-0.0.3.dist-info/entry_points.txt
baekjoon_solver-0.0.3.dist-info/WHEEL
baekjoon_solver-0.0.3.dist-info/METADATA
baekjoon_solver-0.0.3.dist-info/RECORD
