Metadata-Version: 2.1
Name: baekjoon-solver
Version: 0.0.3
Summary: baekjoon solver 문제 풀이
Home-page: https://github.com/2ykwang/baekjoon-solver
License: MIT
Keywords: baekjoon,online judge
Author: Youngkwang Yang
Author-email: immutable000@gmail.com
Requires-Python: >=3.7,<4.0
Classifier: Environment :: Console
Classifier: Framework :: Flake8
Classifier: License :: OSI Approved :: MIT License
Classifier: Operating System :: OS Independent
Classifier: Programming Language :: Python :: 3
Classifier: Programming Language :: Python :: 3.10
Classifier: Programming Language :: Python :: 3.7
Classifier: Programming Language :: Python :: 3.8
Classifier: Programming Language :: Python :: 3.9
Classifier: Topic :: Software Development :: Documentation
Classifier: Topic :: Software Development :: Libraries :: Python Modules
Classifier: Topic :: Software Development :: Quality Assurance
Requires-Dist: beautifulsoup4 (==4.11.1)
Requires-Dist: colorama (==0.4.5)
Requires-Dist: httpx (==0.23.0)
Project-URL: Repository, https://github.com/2ykwang/baekjoon-solver
